progresso.py
progresso-0.1.0.dist-info/LICENSE
progresso-0.1.0.dist-info/METADATA
progresso-0.1.0.dist-info/WHEEL
progresso-0.1.0.dist-info/top_level.txt
progresso-0.1.0.dist-info/RECORD
