Metadata-Version: 2.1
Name: progresso
Version: 0.1.0
Summary: Make iterators yield progress
Author-email: Jose Tiago Macara Coutinho <coutinhotiago@gmail.com>
License: GPL-3.0-or-later
Project-URL: Documentation, https://tiagocoutinho.github.io/progresso/
Project-URL: Homepage, https://github.com/tiagocoutinho/progresso
Project-URL: Source, https://github.com/tiagocoutinho/progresso
Classifier: Development Status :: 4 - Beta
Classifier: Intended Audience :: Developers
Classifier: License :: OSI Approved :: GNU General Public License v3 (GPLv3)
Classifier: Programming Language :: Python :: 3
Classifier: Programming Language :: Python :: 3.9
Classifier: Programming Language :: Python :: 3.10
Classifier: Programming Language :: Python :: 3.11
Classifier: Programming Language :: Python :: 3.12
Requires-Python: >=3.9
License-File: LICENSE
Requires-Dist: typing-extensions <5,>=4.6 ; python_version < "3.12"
Provides-Extra: dev
Requires-Dist: build >=0.10.0 ; extra == 'dev'
Requires-Dist: twine >=4.0.2 ; extra == 'dev'
Requires-Dist: pytest >=7 ; extra == 'dev'
Requires-Dist: pytest-cov >=4 ; extra == 'dev'
Requires-Dist: hypothesis >=6 ; extra == 'dev'
Requires-Dist: ruff >=0.3.0 ; extra == 'dev'
Provides-Extra: docs
Requires-Dist: mkdocs ; extra == 'docs'
Requires-Dist: mkdocs-material ; extra == 'docs'
Requires-Dist: mkdocstrings[python] ; extra == 'docs'
Requires-Dist: pygments ; extra == 'docs'
Requires-Dist: pymdown-extensions ; extra == 'docs'
